phue/__init__.py
phue/__main__.py
phue/bridge.py
phue/exceptions.py
phue/group.py
phue/light.py
phue/scene.py
phue/sensor.py
phue/_internal/__init__.py
phue/_internal/console.py
phue2-0.0.4.dist-info/METADATA
phue2-0.0.4.dist-info/WHEEL
phue2-0.0.4.dist-info/entry_points.txt
phue2-0.0.4.dist-info/licenses/LICENSE
phue2-0.0.4.dist-info/RECORD
