Metadata-Version: 2.4
Name: phue2
Version: 0.0.4
Summary: A Philips Hue Python library
Author: Nathanaël Lécaudé, Nathan Nowack
License: MIT
License-File: LICENSE
Requires-Python: >=3.10
Requires-Dist: httpx
